a8mailer/a8mailer.py
a8mailer-0.1.dist-info/LICENSE
a8mailer-0.1.dist-info/METADATA
a8mailer-0.1.dist-info/WHEEL
a8mailer-0.1.dist-info/top_level.txt
a8mailer-0.1.dist-info/RECORD
