Metadata-Version: 2.1
Name: a8mailer
Version: 0.1
Summary: A package for sending emails using Outlook and SMTP
Home-page: https://github.com/devdp/python-mailer.git
Author: Bramhesh Kumar Srivastava
Author-email: brahmesh1996@gmail.com
License: MIT
Platform: UNKNOWN
Classifier: Programming Language :: Python :: 3
Classifier: License :: OSI Approved :: MIT License
Classifier: Operating System :: OS Independent
License-File: LICENSE
Requires-Dist: email
Requires-Dist: smtplib
